{"6l8g3ggsojJWXRa0v2TGkA==":"graduacin-policas-4-2000x1323.jpg","dcO/Nta24Vkve3jxGoiAsQ==":"objetivos-smart-sabes-como-plantearlos.webp","Ff/SxQ5a/B9aMmhJNCTodA==":"zacatecas-cathedral-mountain-nbs-750x375.jpg","I5FnIi03adUzz3MbpCpR3Q==":"objetivos-generales-y-objetivos-especificos-og-600x315.jpg","V/Oyjh/w8TJsNCxfnrYHNQ==":"df-781x641.jpg","lCmHy6cYGsiGXAusYM9c0Q==":"act-768x674.jpg","NDRiRuBUtGCkCCrd5C0kLA==":"captura%20de%20pantalla%202023-08-10%20145655-886x469.jpg","byunam1eBGmXnKyHEEUdag==":"captura%20de%20pantalla%202023-08-10%20154200-781x326.jpg","TQxJfhoJkvK6V5a6Z8JKIg==":"justif-1024x712.webp","8agVS2b28lsEvfyVaY3TsQ==":"cronograma%20de%20actividades%20que%CC%81%20es%20y%20co%CC%81mo%20hacerlo-1-696x516.jpg","/UoZ9NdCHEqHsRC0MQ19cA==":"actividades-de-trabajo-en-equipo-696x391.png","+9O/JoQQpU6komJVM7yaNA==":"98786352ab62965a07c516ba5d449e8a_l-696x309.jpg","z9HA4C/lG/RlcRNCyEUcCQ==":"control-696x751.png","r4oPfKFGjqURXBhBXMapBg==":"eje4_seguridadpublica-96x96.png","YF+CKDMZdiFxcAloC8xECw==":"captura%20de%20pantalla%202023-08-10%20173657-791x547.jpg","TzpbFxZTheUNcWbHEeWnSw==":"captura%20de%20pantalla%202023-08-10%20173802-805x622.jpg"}